async_lambda/__init__.py
async_lambda/build_config.py
async_lambda/cli.py
async_lambda/client.py
async_lambda/config.py
async_lambda/controller.py
async_lambda/defer.py
async_lambda/env.py
async_lambda/middleware.py
async_lambda/payload_encoder.py
async_lambda/py.typed
async_lambda/util.py
async_lambda/models/__init__.py
async_lambda/models/api_response.py
async_lambda/models/case_insensitive_dict.py
async_lambda/models/task.py
async_lambda/models/events/__init__.py
async_lambda/models/events/api_event.py
async_lambda/models/events/base_event.py
async_lambda/models/events/dynamodb_event.py
async_lambda/models/events/managed_sqs_batch_event.py
async_lambda/models/events/managed_sqs_event.py
async_lambda/models/events/scheduled_event.py
async_lambda/models/events/unmanaged_sqs_event.py
async_lambda/models/mock/mock_context.py
async_lambda/models/mock/mock_event.py
async_lambda_unstable-0.6.5.dist-info/METADATA
async_lambda_unstable-0.6.5.dist-info/WHEEL
async_lambda_unstable-0.6.5.dist-info/entry_points.txt
async_lambda_unstable-0.6.5.dist-info/RECORD
