Metadata-Version: 2.4
Name: async-lambda-unstable
Version: 0.6.5
Summary: A framework for creating AWS Lambda Async Workflows. - Unstable Branch
Author-email: "Nuclei, Inc" <engineering@nuclei.ai>
Requires-Dist: click>=8.0.0
Requires-Dist: typing-extensions>=4.0.0
Provides-Extra: local
Requires-Dist: boto3; extra == 'local'
Requires-Dist: flask<3.0.0,>=2.3.0; extra == 'local'
